val_wrapper/LICENSE
val_wrapper/README.md
val_wrapper/__init__.py
val_wrapper/wrapper.py
val_wrapper/bin/Analyse
val_wrapper/bin/DomainView
val_wrapper/bin/HowWhatWhen
val_wrapper/bin/Instantiate
val_wrapper/bin/Parser
val_wrapper/bin/PinguPlan
val_wrapper/bin/PlanRec
val_wrapper/bin/PlanSeqStep
val_wrapper/bin/PlanToValStep
val_wrapper/bin/Relax
val_wrapper/bin/TIM
val_wrapper/bin/ToFn
val_wrapper/bin/TypeAnalysis
val_wrapper/bin/ValStep
val_wrapper/bin/Validate
val_wrapper/bin/ValueSeq
val_wrapper/bin/libVAL.dylib
val_wrapper-0.2.4.data/scripts/validate.py
val_wrapper-0.2.4.dist-info/LICENSE
val_wrapper-0.2.4.dist-info/METADATA
val_wrapper-0.2.4.dist-info/WHEEL
val_wrapper-0.2.4.dist-info/top_level.txt
val_wrapper-0.2.4.dist-info/RECORD
