Metadata-Version: 2.1
Name: val-wrapper
Version: 0.2.4
Summary: plan validation toolkit
Home-page: https://github.com/LAPKT-dev/val-wrapper
Author: Anubhav Singh
Author-email: anubhav.singh.er@pm.me
License: UNKNOWN
Platform: UNKNOWN
Classifier: Programming Language :: Python :: 3
Classifier: License :: OSI Approved :: BSD License
Classifier: Operating System :: Microsoft :: Windows
Classifier: Operating System :: POSIX :: Linux
Classifier: Operating System :: MacOS
Requires-Python: >=3.7
License-File: LICENSE
